psymple/__init__.py
psymple/abstract.py
psymple/variables.py
psymple/build/__init__.py
psymple/build/abstract.py
psymple/build/assignments.py
psymple/build/compiled_ports.py
psymple/build/errors.py
psymple/build/ported_objects.py
psymple/build/ports.py
psymple/build/system.py
psymple/build/wires.py
psymple/simulate/__init__.py
psymple/simulate/simulation.py
psymple/simulate/solvers/__init__.py
psymple/simulate/solvers/discrete_integrator.py
psymple/simulate/solvers/scipy_integrator.py
psymple/simulate/solvers/solver.py
psymple-1.0.3.dist-info/licenses/LICENSE
psymple-1.0.3.dist-info/METADATA
psymple-1.0.3.dist-info/WHEEL
psymple-1.0.3.dist-info/top_level.txt
psymple-1.0.3.dist-info/RECORD
