Metadata-Version: 2.4
Name: psymple
Version: 1.0.3
Summary: Population Modeling
Author-email: George Simmons <g.simmons@idems.international>, Georg Osang <gosang@idems.international>
Classifier: Programming Language :: Python :: 3
Requires-Python: >=3.10
License-File: LICENSE
Requires-Dist: matplotlib>=3.2.1
Requires-Dist: networkx~=3.1
Requires-Dist: numpy>=1.19.5
Requires-Dist: sympy>=1.9
Requires-Dist: scipy>=1.11
Dynamic: license-file
